README.rst
setup.py
customauth/__init__.py
customauth/admin.py
customauth/apps.py
customauth/models.py
customauth/tests.py
customauth/urls.py
customauth/views.py
customauth/migrations/__init__.py
django_easy_custom_auth.egg-info/PKG-INFO
django_easy_custom_auth.egg-info/SOURCES.txt
django_easy_custom_auth.egg-info/dependency_links.txt
django_easy_custom_auth.egg-info/top_level.txt