Metadata-Version: 2.1
Name: django-easy-custom-auth
Version: 0.1
Summary: A simple Django app to provide user signup, login, change & reset password 
Home-page: UNKNOWN
Author: Mohd Asif
Author-email: asifcoer@gmail.com
License: BSD License
Platform: UNKNOWN
Classifier: Environment :: Web Environment
Classifier: Framework :: Django
Classifier: Intended Audience :: Developers
Classifier: License :: OSI Approved :: BSD License
Classifier: Operating System :: OS Independent
Classifier: Programming Language :: Python
Classifier: Programming Language :: Python :: 3.5
Classifier: Programming Language :: Python :: 3.6
Classifier: Topic :: Internet :: WWW/HTTP
Classifier: Topic :: Internet :: WWW/HTTP :: Dynamic Content
